{"title":"FancyPlugins documentation","subtitle":"Here you\u0027ll find documentation about how to use the plugins, including installation, commands and API.","tips":[{"title":"FancyNpcs","description":"This FancyNpcs is a lightweight and fast plugin that allows you to create custom NPCs to enhance your server.","url":"fancynpcs.html","type":"community"},{"title":"FancyHolograms","description":"FancyHologram is a lightweight and fast plugin that allows you to create holograms with display-entities.","url":"fancyholograms.html","type":"container"}],"main":{"title":"FancyNpcs","data":[{"title":"Getting\n                started","description":"How to install FancyNpcs on your server + how to create your first basic NPC","url":"fn-getting-started.html"},{"title":"Commands","description":"Documentation for all commands of FancyNpcs","url":"fn-commands.html"},{"title":"API","description":"Documentation about the developer API","url":"fn-api.html"}]},"highlighted":{"title":"FancyHolograms","data":[{"title":"Getting\n                started","description":"How to install FancyHolograms on your server + how to create your first text hologram","url":"fh-getting-started.html"},{"title":"Commands","description":"Documentation for all commands of FancyHolograms","url":"fh-commands.html"},{"title":"API","description":"Documentation about the developer API","url":"fh-api.html"}]},"prevNextLinks":{"nextPageUrl":"fancynpcs.html","nextPageTitle":"FancyNpcs"}}